README.md
setup.py
botohelper/__init__.py
botohelper/botohelpermain.py
botohelper/ec2.py
botohelper/iam.py
botohelper/route53.py
botohelper/s3.py
botohelper/utility.py
botohelper.egg-info/PKG-INFO
botohelper.egg-info/SOURCES.txt
botohelper.egg-info/dependency_links.txt
botohelper.egg-info/not-zip-safe
botohelper.egg-info/requires.txt
botohelper.egg-info/top_level.txt