Metadata-Version: 1.1
Name: botohelper
Version: 0.47
Summary: a library to make boto3 easier
Home-page: http://example.com
Author: Banio Carpenter
Author-email: banio@mncarpenters.net
License: BSD
Platform: UNKNOWN
Classifier: Development Status :: 3 - Alpha
Classifier: Environment :: Web Environment
Classifier: Intended Audience :: System Administrators
Classifier: License :: OSI Approved :: BSD License
Classifier: Operating System :: OS Independent
Classifier: Programming Language :: Python :: 3.5
